macronova2py.cpython-39-darwin.so
docs/conf.py
kilopop/__init__.py
kilopop/equation_of_state.py
kilopop/kilonovae.py
kilopop/macronovae_wrapper.py
kilopop/mappings.py
kilopop/population_priors.py
tests/test_equation_of_state.py
tests/test_kilonovae.py
tests/test_macronova_wrapper.py
tests/test_mappings.py
tests/test_population_priors.py
kilopop-1.0.dist-info/LICENSE.md
kilopop-1.0.dist-info/METADATA
kilopop-1.0.dist-info/WHEEL
kilopop-1.0.dist-info/top_level.txt
kilopop-1.0.dist-info/RECORD
