Metadata-Version: 2.1
Name: kilopop
Version: 1.0
Summary: Kilonova and population model used in C. N. Setzer et al. 2022 arxiv:2205.12286v2.
Author-email: "Christian N. Setzer" <aerosetzer@gmail.com>
License: 
Project-URL: homepage, http://github.com/cnsetzer/kilopop
Classifier: Development Status :: 4 - Beta
Classifier: Intended Audience :: Science/Research
Classifier: License :: OSI Approved :: GNU General Public License v3 (GPLv3)
Classifier: Programming Language :: Python :: 3.9
Classifier: Programming Language :: Python :: 3.10
Requires-Python: >=3.9
License-File: LICENSE.md
Requires-Dist: numpy (==1.23.3)
Requires-Dist: pandas
Requires-Dist: george
Requires-Dist: scipy
Requires-Dist: astropy
Requires-Dist: tqdm
Requires-Dist: sncosmo
Provides-Extra: docs
Requires-Dist: sphinx ; extra == 'docs'
Requires-Dist: sphinx-rtd-theme ; extra == 'docs'
Requires-Dist: nbsphinx ; extra == 'docs'
Requires-Dist: pandoc ; extra == 'docs'
Provides-Extra: tests
Requires-Dist: coverage ; extra == 'tests'
